{
  "data": [
    {
      "id": 60,
      "skills": [
        {
          "name": "黄金闪闪",
          "desc": "<p><span style=\"color: rgb(255, 255, 255);\">太乙真人附近800范围内的敌方非英雄单位死亡时，太乙真人和附近的队友都会额外获得20％金币</span></p>",
          "img": "https://lengyibai.gitee.io/wzry-material/hero/taiyizhenren/jineng/0.png",
          "type": ["金币"]
        },
        {
          "name": "意外事故",
          "desc": "<p style=\"text-align: start;\">太乙真人使用炉子炼制药剂，最多持续5秒，炼制结束时或发生爆炸，对周围敌人造成165<span style=\"color: rgb(146, 84, 222);\">（+50%法术攻击）</span>~495<span style=\"color: rgb(146, 84, 222);\">(+165%法术攻击)法术伤害</span>并将其晕眩0.5秒~0.75秒(随技能等级成长最高晕眩1.25秒)。药剂炼制完毕时爆炸命中英雄单位可自动刷新并再释放本技能。</p><p style=\"text-align: start;\"><span style=\"color: rgb(140, 140, 140);\">炼制时间越长，伤害越高，晕眩时间越长。</span></p>",
          "cd": "5",
          "consume": "65",
          "img": "https://lengyibai.gitee.io/wzry-material/hero/taiyizhenren/jineng/1.png",
          "type": ["控制", "法伤", "护盾"],
          "effect": [
            {
              "type": "基础伤害",
              "phase": ["165", "225", "285", "345", "405", "465"]
            },
            {
              "type": "最大伤害",
              "phase": ["495", "675", "855", "1035", "1215", "1395"]
            },
            {
              "type": "护盾",
              "phase": ["300", "350", "400", "450", "500", "550"]
            }
          ]
        },
        {
          "name": "第三只手",
          "desc": "<p><span style=\"color: rgb(255, 255, 255);\">太乙真人伸出触手将自身拉向触手命中的第一个目标，如果是敌方目标，还会造成450</span><span style=\"color: rgb(146, 84, 222);\">(+80%法术攻击)法术伤害</span><span style=\"color: rgb(255, 255, 255);\">并将其晕眩0.5秒。</span></p>",
          "cd": "10",
          "consume": "65",
          "img": "https://lengyibai.gitee.io/wzry-material/hero/taiyizhenren/jineng/2.png",
          "type": ["控制", "法伤"],
          "effect": [
            {
              "type": "基础伤害",
              "phase": ["450", "500", "550", "600", "650", "700"]
            },
            {
              "type": "冷却时间",
              "phase": ["10", "9.2", "8.4", "7.6", "6.8", "6"]
            }
          ]
        },
        {
          "name": "大变活人",
          "desc": "<p><span style=\"color: rgb(255, 255, 255);\">太乙真人召唤替身傀儡，保护自身和附近800范围内血量最低队友，持续3秒，持续期间保护对象被敌方击杀会在2秒后原地复活并获得1600</span><span style=\"color: rgb(146, 84, 222);\">(+200%法术攻击)</span><span style=\"color: rgb(255, 255, 255);\">点生命。没有成功复活任何一个人则返还30%冷却。</span></p>",
          "cd": "70",
          "consume": "150",
          "img": "https://lengyibai.gitee.io/wzry-material/hero/taiyizhenren/jineng/3.png",
          "type": ["复活", "冷却", "回复"],
          "effect": [
            {
              "type": "基础伤害",
              "phase": ["600", "750", "900"]
            },
            {
              "type": "冷却时间",
              "phase": ["70", "65", "60"]
            },
            {
              "type": "复活生命",
              "phase": ["1600", "1350", "3100"]
            }
          ]
        }
      ]
    },
    {
      "id": 67,
      "skills": [
        {
          "name": "纵横兵法",
          "desc": "<p>鬼谷子脱离敌方视野3秒后，可强化下次普攻，对范围目标造成300<span style='color: rgb(106, 57, 201);'>(+45%法术攻击)法术伤害</span>和50%减速，持续1.5秒。</p><p><span style='color: rgb(140, 140, 140);'>如果使用强化攻击时，鬼谷子不处于敌方视野，则【纵横兵法】的冷却将会增加至10秒。</span></p>",
          "img": "https://lengyibai.gitee.io/wzry-material/hero/guiguzi/jineng/0.png",
          "type": ["强化", "法伤", "减速"]
        },
        {
          "name": "先知·神隐",
          "desc": "<p>用玄微子包裹自身进入伪装状态，持续4秒，期间增加40%移速，并对触碰到的每个敌人造成450<span style='color: rgb(106, 57, 201);'>(+60%法术攻击)法术伤害</span>，同时降低该敌人25%的物理和法术防御，持续4秒，每个敌人最多触发1次。</p><p><span style='color: rgb(140, 140, 140);'>伪装效果会在鬼谷子用其他方式伤害敌人时消失。</span><br></p>",
          "cd": 10,
          "consume": 70,
          "img": "https://lengyibai.gitee.io/wzry-material/hero/guiguzi/jineng/1.png",
          "type": ["加速", "伪装", "法伤"],
          "effect": [
            {
              "type": "基础伤害",
              "phase": [450, 540, 630, 720, 810, 900]
            },
            {
              "type": "降低双防",
              "phase": ["25%", "28%", "31%", "34%", "37%", "40%"]
            }
          ]
        },
        {
          "name": "万物有灵",
          "desc": "<p>召唤大量玄微子在自身周围聚集，对范围内敌人每0.5秒造成100<span style='color: rgb(106, 57, 201);'>(+15%法术攻击）法术伤害</span>，持续2秒，2秒后将范围内敌人拉扯到鬼谷子身旁并将其晕眩1秒同时造成400<span style='color: rgb(106, 57, 201);'>(+60%法术攻击)法术伤害</span>。如果该伤害命中敌方英雄，鬼谷子和范围内的队友将获得<span style='color: rgb(106, 57, 201);'>500(+100%法术攻击)</span>点护盾。</p>",
          "type": ["控制", "护盾", "法伤"],
          "cd": 10,
          "consume": 60,
          "img": "https://lengyibai.gitee.io/wzry-material/hero/guiguzi/jineng/2.png",
          "effect": [
            {
              "type": "基础伤害",
              "phase": [100, 120, 140, 160, 180, 200]
            },
            {
              "type": "冷却时间",
              "phase": [10, 9.8, 9.6, 9.4, 9.2, 9]
            },
            {
              "type": "护盾减免",
              "phase": [500, 600, 700, 800, 900, 1000]
            }
          ]
        },
        {
          "name": "先知·雾隐",
          "desc": "<p>命令玄微子包裹自身和1500范围内的队友，1秒后进入伪装状态，期间鬼谷子和队友将增<br>加30%移速，持续4秒，同时获取距离自身最近的敌方英雄视野。</p><p><span style='color: rgb(140, 140, 140);'>伪装状态下，如果使用普攻、技能或对敌方造成负面效果时会立即解除伪装状态。</span></p>",
          "cd": 35,
          "consume": 120,
          "type": ["伪装", "视野", "加速"],
          "img": "https://lengyibai.gitee.io/wzry-material/hero/guiguzi/jineng/3.png",
          "effect": [
            {
              "type": "冷却时间",
              "phase": [35, 30, 25]
            }
          ]
        }
      ]
    },
    {
      "id": 1,
      "skills": [
        {
          "cd": 0,
          "consume": 0,
          "name": "龙鸣",
          "desc": "<p>被动：赵云每损失3%最大生命值，就会获得减少1%所受到的伤害</p>",
          "img": "https://lengyibai.gitee.io/wzry-material/hero/zhaoyun/jineng/0.png",
          "type": ["减伤"]
        },
        {
          "name": "惊雷之云",
          "desc": "<p>赵云执枪向前冲锋，造成190<span style=\"color: rgb(231, 95, 51);\">(+100%物理攻击)物理伤害</span>。 </p><p>冲锋后下次普攻获得强化，对敌人造成65<span style=\"color: rgb(231, 95, 51);\">(+135%物理攻击)物理伤害</span>和25%减速，持续2秒。 </p>",
          "cd": 7,
          "consume": 30,
          "img": "https://lengyibai.gitee.io/wzry-material/hero/zhaoyun/jineng/1.png",
          "type": ["位移", "强化", "物伤"],
          "effect": [
            {
              "type": "基础伤害",
              "phase": ["190", "214", "238", "262", "286", "310"]
            },
            {
              "type": "冷却时间",
              "phase": ["7", "6.4", "5.8", "5.2", "4.6", "4"]
            },
            {
              "type": "额外伤害",
              "phase": ["65", "74", "83", "92", "101", "110"]
            },
            {
              "type": "降低移速",
              "phase": ["25%", "30%", "35%", "40%", "45%", "50%"]
            }
          ]
        },
        {
          "name": "破云之龙",
          "desc": "<p>赵云连续4次刺出龙枪，对命中的敌人每次造成120<span style=\"color: rgb(231, 95, 51);\">(+48%物理攻击)物理伤害</span>并回复25<span style=\"color: rgb(231, 95, 51);\">(+12%物理攻击)</span>点生命。</p>",
          "cd": 6,
          "consume": 40,
          "img": "https://lengyibai.gitee.io/wzry-material/hero/zhaoyun/jineng/2.png",
          "type": ["物伤", "回复"],
          "effect": [
            {
              "type": "基础伤害",
              "phase": ["120", "135", "150", "165", "180", "195"]
            },
            {
              "type": "冷却时间",
              "phase": ["6", "5.6", "5.2", "4.8", "4.4", "4"]
            },
            {
              "type": "回复生命",
              "phase": ["25", "32", "39", "46", "53", "60"]
            }
          ]
        },
        {
          "name": "天翔之龙",
          "desc": "<p>赵云跃向空中发动雷霆一击，对范围内的敌人造成350<span style=\"color: rgb(231, 95, 51);\">(+130%物理攻击)物理伤害</span>，并标记为感电目标，范围中心的敌人还会被击飞1秒。</p><p>赵云的普攻和技能伤害对感电目标额外造成30(<span style=\"color: rgb(231, 95, 51);\">+13%物理攻击)</span><span style=\"color: rgb(106, 57, 201);\">法术伤害</span>。</p>",
          "cd": 18,
          "consume": 75,
          "img": "https://lengyibai.gitee.io/wzry-material/hero/zhaoyun/jineng/3.png",
          "type": ["控制", "位移", "物伤"],
          "effect": [
            {
              "type": "基础伤害",
              "phase": ["350", "450", "550"]
            },
            {
              "type": "冷却时间",
              "phase": ["18", "15", "12"]
            },
            {
              "type": "感电伤害",
              "phase": ["30", "45", "60"]
            }
          ]
        }
      ]
    },
    {
      "id": 2,
      "skills": [
        {
          "cd": 0,
          "consume": 0,
          "name": "失心",
          "desc": "<p>被动：妲己技能命中敌人会减少目标30~72点法术防御，持续3秒，最多叠加3层。</p>",
          "img": "https://lengyibai.gitee.io/wzry-material/hero/daji/jineng/0.png",
          "type": ["弱化"]
        },
        {
          "name": "灵魂冲击",
          "desc": "<p>妲己向指定方向挥出灵魂冲击波，对命中的敌人造成570<span style=\"color: rgb(106, 57, 201);\">(+120%法术攻击)法术伤害</span>。</p>",
          "cd": 5,
          "consume": 60,
          "img": "https://lengyibai.gitee.io/wzry-material/hero/daji/jineng/1.png",
          "type": ["法伤"],
          "effect": [
            {
              "type": "基础伤害",
              "phase": ["570", "635", "700", "765", "830", "895"]
            }
          ]
        },
        {
          "name": "偶像魅力",
          "desc": "<p>妲己锁定敌人并抛出魅力爱心，对命中的敌人造成285<span style=\"color: rgb(106, 57, 201);\">(+66%法术加成)点法术伤害</span>和1.5秒眩晕</p>",
          "cd": 10,
          "consume": 80,
          "img": "https://lengyibai.gitee.io/wzry-material/hero/daji/jineng/2.png",
          "type": ["控制", "法伤"],
          "effect": [
            {
              "type": "基础伤害",
              "phase": ["285", "320", "355", "390", "425", "460"]
            },
            {
              "type": "冷却时间",
              "phase": ["10", "9.4", "8.8", "8.2", "7.6", "7"]
            }
          ]
        },
        {
          "name": "女王崇拜",
          "desc": "<p>妲己放出5团狐火,，狐火随机攻击范围内的敌人，每团狐火造成325<span style=\"color: rgb(106, 57, 201);\">(+75%法术加成)点法术伤害</span>。</p><p><span style=\"color: rgb(140, 140, 140);\">当多团狐火命中同一个目标时，后续狐火开始只造成50%伤害</span></p>",
          "cd": 18,
          "consume": 120,
          "img": "https://lengyibai.gitee.io/wzry-material/hero/daji/jineng/3.png",
          "type": ["法伤"],
          "effect": [
            {
              "type": "基础伤害",
              "phase": ["325", "405", "485"]
            },
            {
              "type": "冷却时间",
              "phase": ["18", "15", "12"]
            }
          ]
        }
      ]
    },
    {
      "id": 3,
      "skills": [
        {
          "cd": 0,
          "consume": 0,
          "name": "哀歌",
          "desc": "<p>高渐离的普攻和技能可视作弹奏，每三次演奏后的下次普攻会强化为能量和弦，对路径上的敌人造成280<span style=\"color: rgb(106, 57, 201);\">(+80%法术攻击)法术伤害</span>。</p>",
          "img": "https://lengyibai.gitee.io/wzry-material/hero/gaojianli/jineng/0.png",
          "type": ["强化", "法伤"]
        },
        {
          "name": "狂歌",
          "desc": "<p>高渐离弹奏出音符，对范围内至多2名敌人造成350<span style=\"color: rgb(106, 57, 201);\">(+47%法术攻击)法术伤害</span>。音符命中敌人后会向附近的敌人进行弹射，音符至多弹射2次。</p><p><span style=\"color: rgb(140, 140, 140);\">当多个音符命中同一目标时，后续音符只造成30%伤害。</span></p>",
          "cd": 7,
          "consume": 80,
          "img": "https://lengyibai.gitee.io/wzry-material/hero/gaojianli/jineng/1.png",
          "type": ["法伤"],
          "effect": [
            {
              "type": "基础伤害",
              "phase": ["350", "410", "470", "530", "590", "650"]
            }
          ]
        },
        {
          "name": "离歌",
          "desc": "<p>高渐离震慑琴弦，对附近敌人造成500<span style=\"color: rgb(106, 57, 201);\">(+65%法术攻击)点法术伤害</span>和35%减速，持续2秒。每命中一个英雄将回复125<span style=\"color: rgb(106, 57, 201);\">(+16%法术攻击)</span>生命值。</p>",
          "cd": 10,
          "consume": 70,
          "img": "https://lengyibai.gitee.io/wzry-material/hero/gaojianli/jineng/2.png",
          "type": ["法伤", "回复", "减速"],
          "effect": [
            {
              "type": "基础伤害",
              "phase": ["500", "560", "620", "680", "740", "800"]
            },
            {
              "type": "冷却时间",
              "phase": ["10", "9.4", "8.8", "8.2", "7.6", "7"]
            },
            {
              "type": "降低移速",
              "phase": ["35%", "40%", "45%", "50%", "55%", "60%"]
            },
            {
              "type": "回复生命",
              "phase": ["125", "140", "155", "170", "185", "200"]
            }
          ]
        },
        {
          "name": "魔音贯耳",
          "desc": "<p>高渐离激情演奏，持续5秒，每0.5秒弹奏一下，造成200<span style=\"color: rgb(106, 57, 201);\">(+20%法术攻击)法术伤害</span>。演奏开始时高渐离增加70%移速，3秒内随时间衰减。演奏持续期间自身获得15%减伤，附近每有一个敌方英雄，额外再获得5%减伤。</p>",
          "cd": 45,
          "consume": 140,
          "img": "https://lengyibai.gitee.io/wzry-material/hero/gaojianli/jineng/3.png",
          "type": ["法伤", "加速", "减伤"],
          "effect": [
            {
              "type": "基础伤害",
              "phase": ["200", "275", "350"]
            },
            {
              "type": "冷却时间",
              "phase": ["45", "37.5", "30"]
            }
          ]
        }
      ]
    },
    {
      "id": 4,
      "skills": [
        {
          "cd": 0,
          "consume": 0,
          "name": "反击之镰",
          "desc": "<p>白起造成或受到伤害时会获得暗影之力，增加移速和治疗效果，最多增加70点移速和80%的治疗效果。</p>",
          "img": "https://lengyibai.gitee.io/wzry-material/hero/baiqi/jineng/0.png",
          "type": ["强化", "加速"]
        },
        {
          "name": "血之回响",
          "desc": "<p>（可蓄力）白起回旋大镰血洗四方，对敌人造成100<span style=\"color: rgb(231, 95, 51);\">(+33%物理攻击)物理伤害</span>，自身回复2%最大生命。</p><p><span style=\"color: rgb(235, 144, 58);\">被动：白起受伤时有20%几率释放【血之回响】。</span></p><p><span style=\"color: rgb(140, 140, 140);\">蓄力越久，伤害和回复越高，最多造成3倍的伤害和回复。只命中非英雄单位时效果减半。</span></p>",
          "cd": 5,
          "consume": 0,
          "img": "https://lengyibai.gitee.io/wzry-material/hero/baiqi/jineng/1.png",
          "type": ["物伤", "回复"],
          "effect": [
            {
              "type": "基础伤害",
              "phase": ["100", "180", "260", "340", "420", "500"]
            }
          ]
        },
        {
          "name": "死神之镰",
          "desc": "<p>白起召唤镰刀，1.2秒后收回镰刀并拉回路径上的敌人，造成200<span style=\"color: rgb(231, 95, 51);\">(+100%物理攻击)</span><span style=\"color: rgb(106, 57, 201);\">法术伤害</span>和50%减速，持续2.5秒。</p><p><span style=\"color: rgb(235, 144, 58);\">被动：白起对生命低于30%的目标会额外造成30%伤害。</span></p>",
          "cd": 14,
          "consume": 0,
          "img": "https://lengyibai.gitee.io/wzry-material/hero/baiqi/jineng/2.png",
          "type": ["控制", "物伤", "强化"],
          "effect": [
            {
              "type": "基础伤害",
              "phase": ["200", "230", "260", "290", "320", "350"]
            },
            {
              "type": "冷却时间",
              "phase": ["14", "13", "12", "11", "10", "9"]
            }
          ]
        },
        {
          "name": "傲慢嘲讽",
          "desc": "<p>白起立即充满暗影之力，向指定位置跳跃，造成300<span style=\"color: rgb(231, 95, 51);\">(+100%物理攻击)</span><span style=\"color: rgb(106, 57, 201);\">法术伤害</span>并嘲讽敌人。嘲讽的基础时长为1~1.5秒，白起每1000点额外生命会额外增加0.2秒，最多持续2.5秒。</p>",
          "cd": 40,
          "consume": 0,
          "img": "https://lengyibai.gitee.io/wzry-material/hero/baiqi/jineng/3.png",
          "type": ["控制", "法伤", "强化"],
          "effect": [
            {
              "type": "基础伤害",
              "phase": ["300", "380", "460"]
            },
            {
              "type": "冷却时间",
              "phase": ["40", "35", "30"]
            },
            {
              "type": "嘲讽时长",
              "phase": ["1", "1.3", "1.5"]
            }
          ]
        }
      ]
    },
    {
      "id": 5,
      "skills": [
        {
          "cd": 0,
          "consume": 0,
          "name": "天命之女",
          "desc": "<p>武则天脱离战斗后会增加50点移速，同时每秒会回复2%最大法力（武则天被动效果脱离战斗的触发时间为3秒）。</p>",
          "img": "https://lengyibai.gitee.io/wzry-material/hero/wuzetian/jineng/0.png",
          "type": ["加速"]
        },
        {
          "name": "女帝辉光",
          "desc": "<p>武则天释放能量法球，命中敌人后对范围内的敌人造成360<span style=\"color: rgb(106, 57, 201);\">(+47%法术攻击)法术伤害</span>。</p><p><span style=\"color: rgb(235, 144, 58);\">被动：武则天释放任意两个技能后，【女帝辉光】会立即刷新并得到强化（造成双倍伤害并将目标击飞0.75秒)，持续3秒。</span></p>",
          "cd": 3,
          "consume": 60,
          "img": "https://lengyibai.gitee.io/wzry-material/hero/wuzetian/jineng/1.png",
          "type": ["法伤", "控制"],
          "effect": [
            {
              "type": "基础伤害",
              "phase": ["360", "420", "480", "540", "600", "660"]
            }
          ]
        },
        {
          "name": "女帝威严",
          "desc": "<p>武则天击退敌人并造成250<span style=\"color: rgb(106, 57, 201);\">(+30%法术攻击)法术伤害</span>。如果技能命中敌人，自身会增加30%移速，持续1秒，命中的敌人会减少30%的移速，持续2秒。</p>",
          "cd": 8,
          "consume": 90,
          "img": "https://lengyibai.gitee.io/wzry-material/hero/wuzetian/jineng/2.png",
          "type": ["控制", "加速", "法伤"],
          "effect": [
            {
              "type": "基础伤害",
              "phase": ["250", "280", "310", "340", "370", "400"]
            },
            {
              "type": "冷却时间",
              "phase": ["8", "7.6", "7.2", "6.8", "6.4", "6"]
            },
            {
              "type": "增加移速",
              "phase": ["30%", "34%", "38%", "42%", "46%", "50%"]
            },
            {
              "type": "降低移速",
              "phase": ["30%", "34%", "38%", "42%", "46%", "50%"]
            }
          ]
        },
        {
          "name": "生杀予夺",
          "desc": "<p>武则天在所有敌方英雄脚下召唤法阵并引爆，对范围内敌人造成750<span style=\"color: rgb(106, 57, 201);\">(+75%法术攻击)法术伤害</span>并晕眩1秒，同时获取敌方视野，持续3秒。</p>",
          "cd": 80,
          "consume": 150,
          "img": "https://lengyibai.gitee.io/wzry-material/hero/wuzetian/jineng/3.png",
          "type": ["法伤", "控制", "视野"],
          "effect": [
            {
              "type": "基础伤害",
              "phase": ["750", "925", "1100"]
            },
            {
              "type": "冷却时间",
              "phase": ["80", "70", "60"]
            }
          ]
        }
      ]
    },
    {
      "id": 6,
      "skills": [
        {
          "cd": 0,
          "consume": 0,
          "name": "月光之舞",
          "desc": "<p>露娜每三次的第一次普攻会向敌人发起冲锋。</p><p>露娜的第三次普攻将会额外造成150<span style=\"color: rgb(106, 57, 201);\">(+35%法术攻击)法术伤害</span>并标记敌人。</p><p><span style=\"color: rgb(140, 140, 140);\">无法标记机关。露娜每1法术攻击将提升0.03%攻速。</span></p>",
          "img": "https://lengyibai.gitee.io/wzry-material/hero/luna/jineng/0.png",
          "type": ["标记", "强化", "法伤"]
        },
        {
          "name": "弦月斩",
          "desc": "<p>露娜挥出月光冲击波，对命中的敌人造成350<span style=\"color: rgb(106, 57, 201);\">(+51%法术攻击)法术伤害</span>并标记敌人。</p>",
          "cd": 5,
          "consume": 50,
          "img": "https://lengyibai.gitee.io/wzry-material/hero/luna/jineng/1.png",
          "type": ["法伤"],
          "effect": [
            {
              "type": "基础伤害",
              "phase": ["350", "430", "510", "590", "670", "750"]
            }
          ]
        },
        {
          "name": "炙热剑芒",
          "desc": "<p>露娜牵引附近的敌人造成120<span style=\"color: rgb(106, 57, 201);\">(+31%法术攻击)法术伤害</span>并晕眩0.5秒，同时获得400<span style=\"color: rgb(106, 57, 201);\">(+80%法术攻击)</span>点护盾并减少其50%移速，持续2秒。</p><p><span style=\"color: rgb(140, 140, 140);\">同时会标记被牵引的敌人。</span></p>",
          "cd": 8,
          "consume": 50,
          "img": "https://lengyibai.gitee.io/wzry-material/hero/luna/jineng/2.png",
          "type": ["控制", "护盾", "法伤"],
          "effect": [
            {
              "type": "基础伤害",
              "phase": ["120", "135", "150", "165", "180", "195"]
            },
            {
              "type": "护盾减免",
              "phase": ["400", "470", "540", "610", "680", "750"]
            }
          ]
        },
        {
          "name": "新月突击",
          "desc": "<p>露娜发起突击，对路径上敌人造成400<span style=\"color: rgb(106, 57, 201);\">(+60%法术攻击)法术伤害</span>。</p><p>如果露娜命中了被标记的敌人，将会刷新【新月突击】的冷却。</p>",
          "cd": 25,
          "consume": 70,
          "img": "https://lengyibai.gitee.io/wzry-material/hero/luna/jineng/3.png",
          "type": ["位移", "冷却", "法伤"],
          "effect": [
            {
              "type": "基础伤害",
              "phase": ["400", "525", "650"]
            },
            {
              "type": "冷却时间",
              "phase": ["25", "20", "15"]
            }
          ]
        }
      ]
    }
  ]
}
